README.rst
setup.py
djorm_ext_pgjson.egg-info/PKG-INFO
djorm_ext_pgjson.egg-info/SOURCES.txt
djorm_ext_pgjson.egg-info/dependency_links.txt
djorm_ext_pgjson.egg-info/not-zip-safe
djorm_ext_pgjson.egg-info/top_level.txt
djorm_pgjson/__init__.py
djorm_pgjson/fields.py