Metadata-Version: 1.1
Name: djorm-ext-pgjson
Version: 0.1
Summary: PostgreSQL native json field support for Django.
Home-page: https://github.com/niwibe/djorm-ext-pgjson
Author: Andrey Antukh
Author-email: niwi@niwi.be
License: BSD
Keywords: django,postgresql,pgsql,json,field
Platform: OS Independent
Classifier: Development Status :: 4 - Beta
Classifier: Framework :: Django
Classifier: Intended Audience :: Developers
Classifier: License :: OSI Approved :: BSD License
Classifier: Operating System :: OS Independent
Classifier: Programming Language :: Python
Classifier: Programming Language :: Python :: 2
Classifier: Programming Language :: Python :: 2.7
Classifier: Programming Language :: Python :: 3
Classifier: Programming Language :: Python :: 3.3
Classifier: Topic :: Internet :: WWW/HTTP
